absence/__init__.py
absence/exceptions.py
absence/installers.py
absence/objects.py
absence/py.typed
absence/__/__init__.py
absence/__/imports.py
absence/__/nomina.py
absence-1.1.1.dist-info/METADATA
absence-1.1.1.dist-info/WHEEL
absence-1.1.1.dist-info/licenses/LICENSE.txt
absence-1.1.1.dist-info/RECORD
