Metadata-Version: 2.4
Name: absence
Version: 1.1.1
Summary: Sentinel for absent values.
Project-URL: Homepage, https://github.com/emcd/python-absence
Project-URL: Documentation, https://emcd.github.io/python-absence
Project-URL: Download, https://pypi.org/project/absence/#files
Project-URL: Source Code, https://github.com/emcd/python-absence
Project-URL: Issue Tracker, https://github.com/emcd/python-absence/issues
Author-email: Eric McDonald <emcd@users.noreply.github.com>
License-Expression: Apache-2.0
License-File: LICENSE.txt
Classifier: Development Status :: 5 - Production/Stable
Classifier: License :: OSI Approved :: Apache Software License
Classifier: Programming Language :: Python :: 3 :: Only
Classifier: Programming Language :: Python :: 3.10
Classifier: Programming Language :: Python :: 3.11
Classifier: Programming Language :: Python :: 3.12
Classifier: Programming Language :: Python :: 3.13
Classifier: Programming Language :: Python :: Implementation :: CPython
Classifier: Programming Language :: Python :: Implementation :: PyPy
Requires-Python: >=3.10
Requires-Dist: classcore
Requires-Dist: dynadoc
Requires-Dist: falsifier~=2.1
Requires-Dist: typing-extensions
